AUTHORS
LICENSE
MANIFEST.in
README.md
setup.py
example/README.md
example/load.py
example/queries.py
example/requirements.txt
xapiand/__init__.py
xapiand/collections.py
xapiand/compat.py
xapiand/connection_pool.py
xapiand/constants.py
xapiand/exceptions.py
xapiand/serializer.py
xapiand/transport.py
xapiand.egg-info/PKG-INFO
xapiand.egg-info/SOURCES.txt
xapiand.egg-info/dependency_links.txt
xapiand.egg-info/requires.txt
xapiand.egg-info/top_level.txt
xapiand/client/__init__.py
xapiand/client/documents.py
xapiand/client/indices.py
xapiand/connection/__init__.py
xapiand/connection/base.py
xapiand/connection/http_requests.py
xapiand/connection/http_urllib3.py
xapiand/connection/pooling.py
xapiand/helpers/__init__.py
xapiand/helpers/bulk.py
xapiand/helpers/errors.py
xapiand/helpers/reindex.py
xapiand/helpers/test.py
xapiand/utils/__init__.py
xapiand/utils/client.py
xapiand/utils/hashes.py
xapiand/utils/serialise.py
xapiand/utils/sortable.py